powerdns_client/__init__.py
powerdns_client/api_client.py
powerdns_client/configuration.py
powerdns_client/rest.py
powerdns_client/api/__init__.py
powerdns_client/api/config_api.py
powerdns_client/api/search_api.py
powerdns_client/api/servers_api.py
powerdns_client/api/stats_api.py
powerdns_client/api/tsigkey_api.py
powerdns_client/api/zonecryptokey_api.py
powerdns_client/api/zonemetadata_api.py
powerdns_client/api/zones_api.py
powerdns_client/models/__init__.py
powerdns_client/models/cache_flush_result.py
powerdns_client/models/comment.py
powerdns_client/models/config_setting.py
powerdns_client/models/cryptokey.py
powerdns_client/models/error.py
powerdns_client/models/map_statistic_item.py
powerdns_client/models/metadata.py
powerdns_client/models/record.py
powerdns_client/models/ring_statistic_item.py
powerdns_client/models/rr_set.py
powerdns_client/models/search_result.py
powerdns_client/models/search_result_comment.py
powerdns_client/models/search_result_record.py
powerdns_client/models/search_result_zone.py
powerdns_client/models/search_results.py
powerdns_client/models/server.py
powerdns_client/models/servers.py
powerdns_client/models/simple_statistic_item.py
powerdns_client/models/statistic_item.py
powerdns_client/models/tsig_key.py
powerdns_client/models/zone.py
powerdns_client/models/zones.py
test/__init__.py
test/test_cache_flush_result.py
test/test_comment.py
test/test_config_api.py
test/test_config_setting.py
test/test_cryptokey.py
test/test_error.py
test/test_map_statistic_item.py
test/test_metadata.py
test/test_record.py
test/test_ring_statistic_item.py
test/test_rr_set.py
test/test_search_api.py
test/test_search_result.py
test/test_search_result_comment.py
test/test_search_result_record.py
test/test_search_result_zone.py
test/test_search_results.py
test/test_server.py
test/test_servers.py
test/test_servers_api.py
test/test_simple_statistic_item.py
test/test_statistic_item.py
test/test_stats_api.py
test/test_tsig_key.py
test/test_tsigkey_api.py
powerdns_client-1.0.4.dist-info/LICENSE
powerdns_client-1.0.4.dist-info/METADATA
powerdns_client-1.0.4.dist-info/WHEEL
powerdns_client-1.0.4.dist-info/top_level.txt
powerdns_client-1.0.4.dist-info/RECORD
