Metadata-Version: 2.1
Name: powerdns-client
Version: 1.0.4
Summary: PowerDNS Authoritative HTTP API
Home-page: https://github.com/nrfta/python-powerdns-client
Author-email: 
License: UNKNOWN
Keywords: Swagger,PowerDNS Authoritative HTTP API
Platform: UNKNOWN
Requires-Dist: certifi (>=2017.4.17)
Requires-Dist: python-dateutil (>=2.1)
Requires-Dist: six (>=1.10)
Requires-Dist: urllib3 (>=1.23)
